letterparser/__init__.py
letterparser/build.py
letterparser/conf.py
letterparser/docker_lib.py
letterparser/generate.py
letterparser/parse.py
letterparser/utils.py
letterparser/zip_lib.py
letterparser-0.14.0.dist-info/LICENSE
letterparser-0.14.0.dist-info/METADATA
letterparser-0.14.0.dist-info/WHEEL
letterparser-0.14.0.dist-info/top_level.txt
letterparser-0.14.0.dist-info/RECORD
