Metadata-Version: 2.1
Name: letterparser
Version: 0.14.0
Summary: Decision letter and author response document parser.
Home-page: https://github.com/elifesciences/decision-letter-parser
Maintainer: eLife Sciences Publications Ltd.
Maintainer-email: tech-team@elifesciences.org
License: MIT
Classifier: Development Status :: 3 - Alpha
Classifier: Intended Audience :: Developers
Classifier: License :: OSI Approved :: MIT License
Classifier: Programming Language :: Python :: 3
License-File: LICENSE
Requires-Dist: elifearticle
Requires-Dist: elifetools
Requires-Dist: jatsgenerator (>=0.3.0)
Requires-Dist: pypandoc
Requires-Dist: requests
Requires-Dist: docker
Requires-Dist: configparser
